itflex_sdk/__init__.py
itflex_sdk/common.py
itflex_sdk/consts.py
itflex_sdk/datetime.py
itflex_sdk/errors.py
itflex_sdk/paginate.py
itflex_sdk/requester.py
itflex_sdk/sdk.py
itflex_sdk/auth/__init__.py
itflex_sdk/auth/apikey.py
itflex_sdk/auth/auth.py
itflex_sdk/auth/role.py
itflex_sdk/auth/scope.py
itflex_sdk/auth/user.py
itflex_sdk/openvpn/__init__.py
itflex_sdk/openvpn/ca.py
itflex_sdk/openvpn/client_s2s.py
itflex_sdk/openvpn/client_s2u.py
itflex_sdk/openvpn/instance.py
itflex_sdk/openvpn/instance_model.py
itflex_sdk/openvpn/openvpn.py
itflex_sdk-0.0.2.dist-info/LICENSE
itflex_sdk-0.0.2.dist-info/METADATA
itflex_sdk-0.0.2.dist-info/WHEEL
itflex_sdk-0.0.2.dist-info/top_level.txt
itflex_sdk-0.0.2.dist-info/RECORD
